{
  "link": "https://www.shopdorsey.com/collections/rings/products/tate-lab-blue-sapphire-ring-gold",
  "title": "TATE LAB BLUE SAPPHIRE RING, GOLD",
  "imgContainer": [
    "//www.shopdorsey.com/cdn/shop/files/Group2_be79f94a-090b-4aa2-960b-3c634eab387e_2400x2400.png?v=1726079304",
    "//www.shopdorsey.com/cdn/shop/files/Group4_24064582-56b9-4bf2-9b43-a0a9781b206c_2400x2400.png?v=1726079303",
    "//www.shopdorsey.com/cdn/shop/files/DORSEYLAKSHMI33913_fe152731-5e2a-4f4e-ac81-30eae76dffdb_2400x2400.png?v=1726092948",
    "//www.shopdorsey.com/cdn/shop/files/Group10_063d5a6e-ddc4-4640-ac16-67e6a443b911_2400x2400.png?v=1726092947"
  ],
  "vidContainer": [],
  "description": [
    "\n        The Tate Cocktail Ring features a 2.5-carat oval lab-grown blue sapphire, encircled by oval blue sapphires and round white sapphires or diamonds. \n Holiday Production Time: This made to order ring ships 5 - 7 weeks from purchase date.   Please place your order by November 1st for guaranteed delivery before December 25th. Orders placed after this date cannot be guaranteed to arrive in time for the holidays. \nCustom styles can only be returned for store credit.\n      "
  ],
  "details": "\n                \n\n\n  Metal: 18k gold coated silver or 14k yellow gold\n\nCenter stone: Lab-grown blue sapphire\nInner halo: Lab-grown blue sapphire\nOuter halo: Lab-grown white sapphire or diamond\nStone shape: Oval cut center and inner halo, round cut outer halo\n\nSize: 4-10\n\n\nLab-Grown Blue Sapphire and White Sapphire Carat: \n\n\n  Blue Sapphire Center Oval: 2.5 CTW DEW\n\nBlue Sapphire Inner Halo: 1.92 CTW DEW\n\nWhite Sapphire Outer Halo: 0.45 CTW DEW \n\n\nLab-Grown Blue Sapphire and Diamond Carat: \n\n\n Blue Sapphire Center Oval: 2.5 CTW DEW\n\nBlue Sapphire Inner Halo: 1.92 CTW DEW\nDiamond Outer Halo: 0.45 CTW E/F VS1 \n\nStone Color: E/F\nStone Clarity: VS1 \nWhat is Lab-Grown?\n              ",
  "basePrice": "$600"
}