{
  "link": "https://www.shopdorsey.com/collections/necklaces/products/clarette-1",
  "title": "CLARETTE LINK NECKLACE, GOLD",
  "imgContainer": [
    "//www.shopdorsey.com/cdn/shop/files/CLARETTE_2400x2400.jpg?v=1699294909",
    "//www.shopdorsey.com/cdn/shop/files/claretteside_2400x2400.png?v=1728513805",
    "//www.shopdorsey.com/cdn/shop/files/preview_images/38656e5b570e4effbe4a1ae76e625d26.thumbnail.0000000000_1024x.jpg?v=1723224781",
    "//www.shopdorsey.com/cdn/shop/files/DORSEYNEWNESS243911_2400x2400.png?v=1728513660"
  ],
  "vidContainer": [],
  "description": [
    "\n        \nThe Clarette necklace is our most beloved necklace. The go-anywhere, do-anything revival collar is big enough to layer atop sweaters and sleek enough to wear bare chested. Add some weight to your fall shift in tone. She's the necklace that changes everything. \n\n      "
  ],
  "details": "\n                Metal: 18K Gold-coated brass \nSize: 16 inches\n\n\nClosure: Custom clasp\nWidth: \n13.44 mm\n\n              ",
  "basePrice": "$590"
}