{
  "link": "https://www.shopdorsey.com/collections/rivieres-1/products/moss-4-prong-riviere",
  "title": "MOSS ROUND CUT, 3MM LAB WHITE SAPPHIRE SILVER RIVIÈRE NECKLACE",
  "imgContainer": [
    "//www.shopdorsey.com/cdn/shop/products/43_2400x2400.jpg?v=1659330885",
    "//www.shopdorsey.com/cdn/shop/products/44_2400x2400.jpg?v=1677777313",
    "//www.shopdorsey.com/cdn/shop/files/preview_images/4247704e2b064bd5a593e127ad343ae0.thumbnail.0000000000_1024x.jpg?v=1728509257",
    "//www.shopdorsey.com/cdn/shop/files/Group10_13c4dcf6-abfa-4c33-8ca4-685629a8b3b8_2400x2400.png?v=1728508623",
    "//www.shopdorsey.com/cdn/shop/files/preview_images/d6bb96e0cc984239b772c9e369971dba.thumbnail.0000000000_1024x.jpg?v=1723215784",
    "//www.shopdorsey.com/cdn/shop/files/preview_images/85b1f598a95c45eb8a54326b38b8f851.thumbnail.0000000000_1024x.jpg?v=1723215414"
  ],
  "vidContainer": [],
  "description": [
    "\n        \n\nA Dorsey staple, the 4-prong Kate necklace is an easy go-to layering piece. Now available in 3MM lab-grown white sapphires for a daintier look than our Kate necklace (which is 3.75 MM), Moss is set with fine jewelry integrity and clasped securely with double safety hooks. Put it on, leave it on, and wear it with everything.\n      "
  ],
  "details": "\n                \nMetal: Sterling Silver\nSetting: 4-prong\nStone Type: Lab-grown white sapphire\nStone Shape: Round Cut\nStone Size: 3MM\n\n\n\n15 inches, 11.80 CTW DEW\n16 inches, 12.60 CTW DEW\n18 inches, 14.00 CTW DEW\n20 inches, 15.80 CTW DEW\n\nWhat is Lab-Grown?\n              ",
  "basePrice": "$650"
}